recs_searcher/__init__.py
recs_searcher/base.py
recs_searcher/api/__init__.py
recs_searcher/api/api.py
recs_searcher/augmentation/__init__.py
recs_searcher/augmentation/_actions.py
recs_searcher/augmentation/_base.py
recs_searcher/augmentation/_char_aug.py
recs_searcher/augmentation/_word_aug.py
recs_searcher/dataset/__init__.py
recs_searcher/dataset/_base.py
recs_searcher/dataset/_dataframes.py
recs_searcher/dataset/data/__init__.py
recs_searcher/dataset/data/address_krasnoyarsk.csv
recs_searcher/dataset/data/city_russia.csv
recs_searcher/dataset/data/company_russia.csv
recs_searcher/dataset/data/exoplanets.csv
recs_searcher/dataset/data/medical_supplies.csv
recs_searcher/dataset/data/mobile_phones.csv
recs_searcher/dataset/data/russian_dictionary.csv
recs_searcher/dataset/data/video_games.csv
recs_searcher/embeddings/__init__.py
recs_searcher/embeddings/_base.py
recs_searcher/explain/__init__.py
recs_searcher/explain/_base.py
recs_searcher/preprocessing/__init__.py
recs_searcher/preprocessing/_base_clear.py
recs_searcher/preprocessing/_base_normalize.py
recs_searcher/similarity_search/__init__.py
recs_searcher/similarity_search/_base.py
recs_searcher/similarity_search/_validate.py
recs_searcher/utils/__init__.py
recs_searcher/utils/_concat_embeddings.py
recs_searcher/utils/_create_date_name.py
recs_searcher/utils/_distances.py
recs_searcher-0.1.1.dist-info/LICENSE
recs_searcher-0.1.1.dist-info/METADATA
recs_searcher-0.1.1.dist-info/WHEEL
recs_searcher-0.1.1.dist-info/top_level.txt
recs_searcher-0.1.1.dist-info/RECORD
