Metadata-Version: 2.1
Name: recs-searcher
Version: 0.1.1
Summary: Search engine and registry error corrector
Home-page: https://github.com/sheriff1max/recs-searcher
Author: sheriff1max
Author-email: kobelevmaxim48@gmail.com
Project-URL: Bug tracker, https://github.com/sheriff1max/recs-searcher/issues
Keywords: python searcher corrector faiss chroma-bd embeddings
Classifier: Programming Language :: Python :: 3
Requires-Python: >=3.10
License-File: LICENSE
Requires-Dist: fastapi ==0.104.1
Requires-Dist: chromadb
Requires-Dist: datasets
Requires-Dist: faiss-cpu
Requires-Dist: sentence-transformers
Requires-Dist: pymorphy3
Requires-Dist: scikit-learn
Requires-Dist: spacy
Requires-Dist: thefuzz
Requires-Dist: torch
Requires-Dist: torchvision
Requires-Dist: pytest
